MANIFEST.in
setup.py
QBCodeSpecs/__init__.py
QBCodeSpecs.egg-info/PKG-INFO
QBCodeSpecs.egg-info/SOURCES.txt
QBCodeSpecs.egg-info/dependency_links.txt
QBCodeSpecs.egg-info/entry_points.txt
QBCodeSpecs.egg-info/requires.txt
QBCodeSpecs.egg-info/top_level.txt
QBCodeSpecs/antlr4/BufferedTokenStream.py
QBCodeSpecs/antlr4/CodePoints.py
QBCodeSpecs/antlr4/CommonTokenFactory.py
QBCodeSpecs/antlr4/CommonTokenStream.py
QBCodeSpecs/antlr4/FileStream.py
QBCodeSpecs/antlr4/InputStream.py
QBCodeSpecs/antlr4/IntervalSet.py
QBCodeSpecs/antlr4/LL1Analyzer.py
QBCodeSpecs/antlr4/Lexer.py
QBCodeSpecs/antlr4/ListTokenSource.py
QBCodeSpecs/antlr4/Parser.py
QBCodeSpecs/antlr4/ParserInterpreter.py
QBCodeSpecs/antlr4/ParserRuleContext.py
QBCodeSpecs/antlr4/PredictionContext.py
QBCodeSpecs/antlr4/Recognizer.py
QBCodeSpecs/antlr4/RuleContext.py
QBCodeSpecs/antlr4/StdinStream.py
QBCodeSpecs/antlr4/Token.py
QBCodeSpecs/antlr4/TokenStreamRewriter.py
QBCodeSpecs/antlr4/Utils.py
QBCodeSpecs/antlr4/__init__.py
QBCodeSpecs/antlr4/atn/ATN.py
QBCodeSpecs/antlr4/atn/ATNConfig.py
QBCodeSpecs/antlr4/atn/ATNConfigSet.py
QBCodeSpecs/antlr4/atn/ATNDeserializationOptions.py
QBCodeSpecs/antlr4/atn/ATNDeserializer.py
QBCodeSpecs/antlr4/atn/ATNSimulator.py
QBCodeSpecs/antlr4/atn/ATNState.py
QBCodeSpecs/antlr4/atn/ATNType.py
QBCodeSpecs/antlr4/atn/LexerATNSimulator.py
QBCodeSpecs/antlr4/atn/LexerAction.py
QBCodeSpecs/antlr4/atn/LexerActionExecutor.py
QBCodeSpecs/antlr4/atn/ParserATNSimulator.py
QBCodeSpecs/antlr4/atn/PredictionMode.py
QBCodeSpecs/antlr4/atn/SemanticContext.py
QBCodeSpecs/antlr4/atn/Transition.py
QBCodeSpecs/antlr4/atn/__init__.py
QBCodeSpecs/antlr4/dfa/DFA.py
QBCodeSpecs/antlr4/dfa/DFASerializer.py
QBCodeSpecs/antlr4/dfa/DFAState.py
QBCodeSpecs/antlr4/dfa/__init__.py
QBCodeSpecs/antlr4/error/DiagnosticErrorListener.py
QBCodeSpecs/antlr4/error/ErrorListener.py
QBCodeSpecs/antlr4/error/ErrorStrategy.py
QBCodeSpecs/antlr4/error/Errors.py
QBCodeSpecs/antlr4/error/__init__.py
QBCodeSpecs/antlr4/tree/Chunk.py
QBCodeSpecs/antlr4/tree/ParseTreeMatch.py
QBCodeSpecs/antlr4/tree/ParseTreePattern.py
QBCodeSpecs/antlr4/tree/ParseTreePatternMatcher.py
QBCodeSpecs/antlr4/tree/RuleTagToken.py
