Metadata-Version: 1.0
Name: QBCodeSpecs
Version: 0.0.9
Summary: QBCodeSpecs
Home-page: https://browser.qq.com/ipad/pc.html
Author: paulineli
Author-email: 109926082@qq.com
License: MIT Licence
Keywords: pip,code,specs
Platform: any
